[
  {
    "name": "Process Start",
    "start": 1607929950126,
    "end": 1607929950682,
    "duration": 556,
    "pid": 6640,
    "index": 0
  },
  {
    "name": "Application Start",
    "start": 1607929950682,
    "end": 1607929951251,
    "duration": 569,
    "pid": 6640,
    "index": 1
  },
  {
    "name": "Load Plugin",
    "start": 1607929950686,
    "end": 1607929950700,
    "duration": 14,
    "pid": 6640,
    "index": 2
  },
  {
    "name": "Load Config",
    "start": 1607929950700,
    "end": 1607929950720,
    "duration": 20,
    "pid": 6640,
    "index": 3
  },
  {
    "name": "Require(0) config/config.default.js",
    "start": 1607929950701,
    "end": 1607929950701,
    "duration": 0,
    "pid": 6640,
    "index": 4
  },
  {
    "name": "Require(1) node_modules/egg-session/config/config.default.js",
    "start": 1607929950702,
    "end": 1607929950703,
    "duration": 1,
    "pid": 6640,
    "index": 5
  },
  {
    "name": "Require(2) node_modules/egg-security/config/config.default.js",
    "start": 1607929950703,
    "end": 1607929950703,
    "duration": 0,
    "pid": 6640,
    "index": 6
  },
  {
    "name": "Require(3) node_modules/egg-jsonp/config/config.default.js",
    "start": 1607929950704,
    "end": 1607929950705,
    "duration": 1,
    "pid": 6640,
    "index": 7
  },
  {
    "name": "Require(4) node_modules/egg-onerror/config/config.default.js",
    "start": 1607929950705,
    "end": 1607929950705,
    "duration": 0,
    "pid": 6640,
    "index": 8
  },
  {
    "name": "Require(5) node_modules/egg-i18n/config/config.default.js",
    "start": 1607929950706,
    "end": 1607929950706,
    "duration": 0,
    "pid": 6640,
    "index": 9
  },
  {
    "name": "Require(6) node_modules/egg-watcher/config/config.default.js",
    "start": 1607929950707,
    "end": 1607929950707,
    "duration": 0,
    "pid": 6640,
    "index": 10
  },
  {
    "name": "Require(7) node_modules/egg-schedule/config/config.default.js",
    "start": 1607929950707,
    "end": 1607929950708,
    "duration": 1,
    "pid": 6640,
    "index": 11
  },
  {
    "name": "Require(8) node_modules/egg-multipart/config/config.default.js",
    "start": 1607929950708,
    "end": 1607929950708,
    "duration": 0,
    "pid": 6640,
    "index": 12
  },
  {
    "name": "Require(9) node_modules/egg-development/config/config.default.js",
    "start": 1607929950709,
    "end": 1607929950709,
    "duration": 0,
    "pid": 6640,
    "index": 13
  },
  {
    "name": "Require(10) node_modules/egg-logrotator/config/config.default.js",
    "start": 1607929950710,
    "end": 1607929950710,
    "duration": 0,
    "pid": 6640,
    "index": 14
  },
  {
    "name": "Require(11) node_modules/egg-static/config/config.default.js",
    "start": 1607929950710,
    "end": 1607929950711,
    "duration": 1,
    "pid": 6640,
    "index": 15
  },
  {
    "name": "Require(12) node_modules/egg-view/config/config.default.js",
    "start": 1607929950711,
    "end": 1607929950712,
    "duration": 1,
    "pid": 6640,
    "index": 16
  },
  {
    "name": "Require(13) node_modules/egg-mysql/config/config.default.js",
    "start": 1607929950712,
    "end": 1607929950712,
    "duration": 0,
    "pid": 6640,
    "index": 17
  },
  {
    "name": "Require(14) node_modules/egg-jwt/config/config.default.js",
    "start": 1607929950713,
    "end": 1607929950713,
    "duration": 0,
    "pid": 6640,
    "index": 18
  },
  {
    "name": "Require(15) node_modules/egg-cors/config/config.default.js",
    "start": 1607929950713,
    "end": 1607929950714,
    "duration": 1,
    "pid": 6640,
    "index": 19
  },
  {
    "name": "Require(16) node_modules/egg-validate/config/config.default.js",
    "start": 1607929950714,
    "end": 1607929950714,
    "duration": 0,
    "pid": 6640,
    "index": 20
  },
  {
    "name": "Require(17) node_modules/egg/config/config.default.js",
    "start": 1607929950715,
    "end": 1607929950715,
    "duration": 0,
    "pid": 6640,
    "index": 21
  },
  {
    "name": "Require(18) config/config.default.js",
    "start": 1607929950716,
    "end": 1607929950716,
    "duration": 0,
    "pid": 6640,
    "index": 22
  },
  {
    "name": "Require(19) node_modules/egg-security/config/config.local.js",
    "start": 1607929950716,
    "end": 1607929950717,
    "duration": 1,
    "pid": 6640,
    "index": 23
  },
  {
    "name": "Require(20) node_modules/egg-watcher/config/config.local.js",
    "start": 1607929950717,
    "end": 1607929950717,
    "duration": 0,
    "pid": 6640,
    "index": 24
  },
  {
    "name": "Require(21) node_modules/egg-view/config/config.local.js",
    "start": 1607929950718,
    "end": 1607929950718,
    "duration": 0,
    "pid": 6640,
    "index": 25
  },
  {
    "name": "Require(22) node_modules/egg/config/config.local.js",
    "start": 1607929950719,
    "end": 1607929950719,
    "duration": 0,
    "pid": 6640,
    "index": 26
  },
  {
    "name": "Load extend/application.js",
    "start": 1607929950720,
    "end": 1607929950769,
    "duration": 49,
    "pid": 6640,
    "index": 27
  },
  {
    "name": "Require(23) node_modules/egg-session/app/extend/application.js",
    "start": 1607929950721,
    "end": 1607929950721,
    "duration": 0,
    "pid": 6640,
    "index": 28
  },
  {
    "name": "Require(24) node_modules/egg-security/app/extend/application.js",
    "start": 1607929950721,
    "end": 1607929950722,
    "duration": 1,
    "pid": 6640,
    "index": 29
  },
  {
    "name": "Require(25) node_modules/egg-jsonp/app/extend/application.js",
    "start": 1607929950723,
    "end": 1607929950723,
    "duration": 0,
    "pid": 6640,
    "index": 30
  },
  {
    "name": "Require(26) node_modules/egg-logrotator/app/extend/application.js",
    "start": 1607929950724,
    "end": 1607929950725,
    "duration": 1,
    "pid": 6640,
    "index": 31
  },
  {
    "name": "Require(27) node_modules/egg-view/app/extend/application.js",
    "start": 1607929950726,
    "end": 1607929950727,
    "duration": 1,
    "pid": 6640,
    "index": 32
  },
  {
    "name": "Require(28) node_modules/egg-jwt/app/extend/application.js",
    "start": 1607929950727,
    "end": 1607929950766,
    "duration": 39,
    "pid": 6640,
    "index": 33
  },
  {
    "name": "Load extend/request.js",
    "start": 1607929950769,
    "end": 1607929950774,
    "duration": 5,
    "pid": 6640,
    "index": 34
  },
  {
    "name": "Require(29) node_modules/egg/app/extend/request.js",
    "start": 1607929950771,
    "end": 1607929950772,
    "duration": 1,
    "pid": 6640,
    "index": 35
  },
  {
    "name": "Load extend/response.js",
    "start": 1607929950774,
    "end": 1607929950778,
    "duration": 4,
    "pid": 6640,
    "index": 36
  },
  {
    "name": "Require(30) node_modules/egg/app/extend/response.js",
    "start": 1607929950775,
    "end": 1607929950776,
    "duration": 1,
    "pid": 6640,
    "index": 37
  },
  {
    "name": "Load extend/context.js",
    "start": 1607929950778,
    "end": 1607929950823,
    "duration": 45,
    "pid": 6640,
    "index": 38
  },
  {
    "name": "Require(31) node_modules/egg-security/app/extend/context.js",
    "start": 1607929950779,
    "end": 1607929950785,
    "duration": 6,
    "pid": 6640,
    "index": 39
  },
  {
    "name": "Require(32) node_modules/egg-jsonp/app/extend/context.js",
    "start": 1607929950785,
    "end": 1607929950786,
    "duration": 1,
    "pid": 6640,
    "index": 40
  },
  {
    "name": "Require(33) node_modules/egg-i18n/app/extend/context.js",
    "start": 1607929950787,
    "end": 1607929950787,
    "duration": 0,
    "pid": 6640,
    "index": 41
  },
  {
    "name": "Require(34) node_modules/egg-multipart/app/extend/context.js",
    "start": 1607929950787,
    "end": 1607929950818,
    "duration": 31,
    "pid": 6640,
    "index": 42
  },
  {
    "name": "Require(35) node_modules/egg-view/app/extend/context.js",
    "start": 1607929950818,
    "end": 1607929950819,
    "duration": 1,
    "pid": 6640,
    "index": 43
  },
  {
    "name": "Require(36) node_modules/egg-validate/app/extend/context.js",
    "start": 1607929950820,
    "end": 1607929950820,
    "duration": 0,
    "pid": 6640,
    "index": 44
  },
  {
    "name": "Require(37) node_modules/egg/app/extend/context.js",
    "start": 1607929950820,
    "end": 1607929950821,
    "duration": 1,
    "pid": 6640,
    "index": 45
  },
  {
    "name": "Load extend/helper.js",
    "start": 1607929950824,
    "end": 1607929950840,
    "duration": 16,
    "pid": 6640,
    "index": 46
  },
  {
    "name": "Require(38) node_modules/egg-security/app/extend/helper.js",
    "start": 1607929950824,
    "end": 1607929950837,
    "duration": 13,
    "pid": 6640,
    "index": 47
  },
  {
    "name": "Require(39) node_modules/egg/app/extend/helper.js",
    "start": 1607929950838,
    "end": 1607929950839,
    "duration": 1,
    "pid": 6640,
    "index": 48
  },
  {
    "name": "Load app.js",
    "start": 1607929950841,
    "end": 1607929950880,
    "duration": 39,
    "pid": 6640,
    "index": 49
  },
  {
    "name": "Require(40) node_modules/egg-session/app.js",
    "start": 1607929950841,
    "end": 1607929950841,
    "duration": 0,
    "pid": 6640,
    "index": 50
  },
  {
    "name": "Require(41) node_modules/egg-security/app.js",
    "start": 1607929950842,
    "end": 1607929950842,
    "duration": 0,
    "pid": 6640,
    "index": 51
  },
  {
    "name": "Require(42) node_modules/egg-onerror/app.js",
    "start": 1607929950843,
    "end": 1607929950849,
    "duration": 6,
    "pid": 6640,
    "index": 52
  },
  {
    "name": "Require(43) node_modules/egg-i18n/app.js",
    "start": 1607929950849,
    "end": 1607929950860,
    "duration": 11,
    "pid": 6640,
    "index": 53
  },
  {
    "name": "Require(44) node_modules/egg-watcher/app.js",
    "start": 1607929950861,
    "end": 1607929950863,
    "duration": 2,
    "pid": 6640,
    "index": 54
  },
  {
    "name": "Require(45) node_modules/egg-schedule/app.js",
    "start": 1607929950863,
    "end": 1607929950864,
    "duration": 1,
    "pid": 6640,
    "index": 55
  },
  {
    "name": "Require(46) node_modules/egg-multipart/app.js",
    "start": 1607929950864,
    "end": 1607929950865,
    "duration": 1,
    "pid": 6640,
    "index": 56
  },
  {
    "name": "Require(47) node_modules/egg-development/app.js",
    "start": 1607929950865,
    "end": 1607929950865,
    "duration": 0,
    "pid": 6640,
    "index": 57
  },
  {
    "name": "Require(48) node_modules/egg-logrotator/app.js",
    "start": 1607929950865,
    "end": 1607929950866,
    "duration": 1,
    "pid": 6640,
    "index": 58
  },
  {
    "name": "Require(49) node_modules/egg-static/app.js",
    "start": 1607929950866,
    "end": 1607929950866,
    "duration": 0,
    "pid": 6640,
    "index": 59
  },
  {
    "name": "Require(50) node_modules/egg-mysql/app.js",
    "start": 1607929950866,
    "end": 1607929950878,
    "duration": 12,
    "pid": 6640,
    "index": 60
  },
  {
    "name": "Require(51) node_modules/egg-jwt/app.js",
    "start": 1607929950878,
    "end": 1607929950878,
    "duration": 0,
    "pid": 6640,
    "index": 61
  },
  {
    "name": "Require(52) node_modules/egg-cors/app.js",
    "start": 1607929950878,
    "end": 1607929950879,
    "duration": 1,
    "pid": 6640,
    "index": 62
  },
  {
    "name": "Require(53) node_modules/egg-validate/app.js",
    "start": 1607929950879,
    "end": 1607929950880,
    "duration": 1,
    "pid": 6640,
    "index": 63
  },
  {
    "name": "Before Start in node_modules/egg-watcher/lib/init.js:15:14",
    "start": 1607929950892,
    "end": 1607929951084,
    "duration": 192,
    "pid": 6640,
    "index": 64
  },
  {
    "name": "Before Start in node_modules/egg-mysql/lib/mysql.js:20:7",
    "start": 1607929950965,
    "end": 1607929951251,
    "duration": 286,
    "pid": 6640,
    "index": 65
  },
  {
    "name": "Load Service",
    "start": 1607929950965,
    "end": 1607929950972,
    "duration": 7,
    "pid": 6640,
    "index": 66
  },
  {
    "name": "Load \"service\" to Context",
    "start": 1607929950965,
    "end": 1607929950972,
    "duration": 7,
    "pid": 6640,
    "index": 67
  },
  {
    "name": "Load Middleware",
    "start": 1607929950972,
    "end": 1607929951061,
    "duration": 89,
    "pid": 6640,
    "index": 68
  },
  {
    "name": "Load \"middlewares\" to Application",
    "start": 1607929950973,
    "end": 1607929951050,
    "duration": 77,
    "pid": 6640,
    "index": 69
  },
  {
    "name": "Load Controller",
    "start": 1607929951061,
    "end": 1607929951064,
    "duration": 3,
    "pid": 6640,
    "index": 70
  },
  {
    "name": "Load \"controller\" to Application",
    "start": 1607929951062,
    "end": 1607929951064,
    "duration": 2,
    "pid": 6640,
    "index": 71
  },
  {
    "name": "Load Router",
    "start": 1607929951064,
    "end": 1607929951067,
    "duration": 3,
    "pid": 6640,
    "index": 72
  },
  {
    "name": "Require(54) app/router.js",
    "start": 1607929951065,
    "end": 1607929951065,
    "duration": 0,
    "pid": 6640,
    "index": 73
  },
  {
    "name": "Before Start in node_modules/egg-core/lib/egg.js:303:10",
    "start": 1607929951065,
    "end": 1607929951076,
    "duration": 11,
    "pid": 6640,
    "index": 74
  }
]